setup.py
dataaugmentation/ExpandTrainingSet.py
dataaugmentation.egg-info/PKG-INFO
dataaugmentation.egg-info/SOURCES.txt
dataaugmentation.egg-info/dependency_links.txt
dataaugmentation.egg-info/not-zip-safe
dataaugmentation.egg-info/requires.txt
dataaugmentation.egg-info/top_level.txt