Metadata-Version: 1.0
Name: dataaugmentation
Version: 0.1
Summary: Data augmentation with TriTraining strategy
Home-page: https://github.com/caleale90/DataAugmentation
Author: Alessandro Calefati
Author-email: caleale90@gmail.com
License: MIT
Keywords: csv data augmentation machine learning
Platform: UNKNOWN
